mlbi/__init__.py
mlbi/bistack.py
mlbi/bitools.py
mlbi/bridge.py
mlbi/datasets.py
mlbi/decomp.py
mlbi/deiso.py
mlbi/load_data.py
mlbi/misc.py
mlbi/pybam.py
mlbi/survival.py
mlbi/data/CCLE_cellline_gene_exp.csv
mlbi/data/CCLE_cellline_info.csv
mlbi/data/CCLE_drug_info.csv
mlbi/data/CCLE_drug_response_auc.csv
mlbi/data/CCLE_drug_response_ec50.csv
mlbi/data/CancerSEEK_clinical_info.csv
mlbi/data/CancerSEEK_comb.csv
mlbi/data/CancerSEEK_protein.csv
mlbi/data/PSID1976.csv
mlbi/data/TCGA_BRCA_clinical_info.csv
mlbi/data/TCGA_BRCA_gene_exp.csv
mlbi/data/Time_series.csv
mlbi/data/Time_series_rev.csv
mlbi/data/metabric_clinical_data_used.csv
mlbi/data/metabric_clinical_info.csv
mlbi/data/metabric_gene_expression.csv
mlbi/data/scores.csv
mlbi_lab-0.3.10.dist-info/licenses/LICENSE
mlbi_lab-0.3.10.dist-info/METADATA
mlbi_lab-0.3.10.dist-info/WHEEL
mlbi_lab-0.3.10.dist-info/entry_points.txt
mlbi_lab-0.3.10.dist-info/top_level.txt
mlbi_lab-0.3.10.dist-info/RECORD
